code-generation/__init__.py
code-generation/playground.py
creao/__init__.py
creao/component/__init__.py
creao/component/data_creator.py
creao/component/evaluator.py
creao/component/finetuner.py
creao/component/extractors/__init__.py
creao/component/extractors/extract_poi.py
creao/component/filters/__init__.py
creao/component/filters/dedup.py
creao/component/filters/filter_question_by_intelligent.py
creao/component/filters/filter_question_by_relevance.py
creao/component/generators/__init__.py
creao/component/generators/creaogenerator.py
creao/component/generators/embed.py
creao/component/mappers/__init__.py
creao/component/mappers/map_interest_to_question_type.py
creao/component/mappers/map_question_type_to_question.py
creao/component/mappers/rewrite_question.py
creao/component/mappers/text_to_persona.py
creao/core/Endpoints.py
creao/core/__init__.py
creao/core/util.py
creao/core/component/__init__.py
creao/core/component/data_component.py
creao/core/component/dedupe_component.py
creao/core/component/filter_component.py
creao/core/component/llm_component.py
creao/core/component/util.py
creao/core/demo/__init__.py
creao/core/demo/rag.py
creao/core/pipeline/__init__.py
creao/core/pipeline/util.py
creao-0.3.51.dist-info/METADATA
creao-0.3.51.dist-info/WHEEL
creao-0.3.51.dist-info/top_level.txt
creao-0.3.51.dist-info/RECORD
