Metadata-Version: 2.1
Name: creao
Version: 0.3.51
Summary: A description of your project
Home-page: https://creao@dev.azure.com/creao/creao/_git/creao
Author: creaoai
Author-email: dev@creao.ai
Classifier: Programming Language :: Python :: 3
Classifier: License :: OSI Approved :: MIT License
Classifier: Operating System :: OS Independent
Requires-Python: >=3.6
Requires-Dist: networkx ==3.3
Requires-Dist: openai ==1.40.6
Requires-Dist: datasets ==2.21.0
